unicorrns/ErrorsBigList.dat
unicorrns/__init__.py
unicorrns/bf4b.txt
unicorrns/chain4b.txt
unicorrns/unicorn.py
unicorrns-0.1.3.dist-info/LICENSE
unicorrns-0.1.3.dist-info/METADATA
unicorrns-0.1.3.dist-info/WHEEL
unicorrns-0.1.3.dist-info/top_level.txt
unicorrns-0.1.3.dist-info/RECORD
