Metadata-Version: 2.1
Name: unicorrns
Version: 0.1.3
Summary: UNIversal Correlations Neutron Stars package
Home-page: 
Author: Peter Shternin
Author-email: pshternin@gmail.com
License: MIT
License-File: LICENSE
